AUTHORS.rst
CONTRIBUTING.rst
LICENSE
MANIFEST.in
README.rst
setup.cfg
setup.py
docs/Makefile
docs/authors.rst
docs/conf.py
docs/contributing.rst
docs/history.rst
docs/index.rst
docs/installation.rst
docs/make.bat
docs/readme.rst
docs/usage.rst
tests/__init__.py
tests/test_tinysa.py
tinysa/__init__.py
tinysa/tinysa.py
tinysa.egg-info/PKG-INFO
tinysa.egg-info/SOURCES.txt
tinysa.egg-info/dependency_links.txt
tinysa.egg-info/not-zip-safe
tinysa.egg-info/top_level.txt