Metadata-Version: 1.1
Name: tinysa
Version: 0.2.0
Summary: Python Boilerplate contains all the boilerplate you need to create a Python package.
Home-page: https://github.com/jun-harashima/tinysa
Author: Jun Harashima
Author-email: j.harashima@gmail.com
License: MIT license
Keywords: tiny suffix array
Platform: UNKNOWN
Classifier: Development Status :: 2 - Pre-Alpha
Classifier: Intended Audience :: Developers
Classifier: License :: OSI Approved :: MIT License
Classifier: Natural Language :: English
Classifier: Programming Language :: Python :: 2
Classifier: Programming Language :: Python :: 2.7
Classifier: Programming Language :: Python :: 3
Classifier: Programming Language :: Python :: 3.4
Classifier: Programming Language :: Python :: 3.5
Classifier: Programming Language :: Python :: 3.6
Classifier: Programming Language :: Python :: 3.7
